cdl_dynamic_crawlers/__init__.py
cdl_dynamic_crawlers/py.typed
cdl_dynamic_crawlers-1.3.1.dist-info/licenses/LICENSE
cdl_dynamic_crawlers-1.3.1.dist-info/METADATA
cdl_dynamic_crawlers-1.3.1.dist-info/WHEEL
cdl_dynamic_crawlers-1.3.1.dist-info/entry_points.txt
cdl_dynamic_crawlers-1.3.1.dist-info/top_level.txt
cdl_dynamic_crawlers-1.3.1.dist-info/RECORD
