Metadata-Version: 2.4
Name: cdl-dynamic-crawlers
Version: 1.3.1
Summary: Load additional crawlers from files
Author-email: NTFSvolume <172021377+NTFSvolume@users.noreply.github.com>
License-Expression: MIT
Project-URL: Repository, https://github.com/NTFSvolume/cdl-dynamic-crawlers
Classifier: Development Status :: 4 - Beta
Classifier: Intended Audience :: Developers
Classifier: Operating System :: OS Independent
Classifier: Programming Language :: Python
Classifier: Programming Language :: Python :: 3
Classifier: Programming Language :: Python :: 3.11
Classifier: Programming Language :: Python :: 3.12
Classifier: Programming Language :: Python :: 3.13
Classifier: Programming Language :: Python :: 3.14
Classifier: Typing :: Typed
Requires-Python: <4.0,>=3.11
License-File: LICENSE
Dynamic: license-file
